[
    {
        "id": "8cedefbf-67aa-4945-9e0b-bc55739614e7",
        "task": "0eaaa82f-70e3-4e63-ac65-d16feda590a4",
        "description": "Worked on Buy Seeds",
        "person": "c08a396d-5b75-433f-87c5-5a57d9669b3f",
        "date": "2026-02-01T20:00:36.665Z",
        "duration": 2162,
        "billable": true,
        "billed": false,
        "status": "pending",
        "approvedBy": null,
        "approvedOn": null,
        "rejectReason": null
    },
    {
        "id": "fe04c629-397e-48d7-a773-b0f72c239447",
        "task": "3ee6c7c3-97c2-4ac8-a2af-ce36ad216ca8",
        "description": "Worked on Prepare Soil",
        "person": "77260c19-e58a-42c9-8cac-e53add3260a4",
        "date": "2026-02-02T20:00:36.665Z",
        "duration": 3299,
        "billable": true,
        "billed": false,
        "status": "pending",
        "approvedBy": null,
        "approvedOn": null,
        "rejectReason": null
    },
    {
        "id": "fafc18ff-35c3-4b5a-97d7-97859451e6ec",
        "task": "eccaa3e5-8643-4a8d-b138-e0a7f0cdc256",
        "description": "Worked on Plant Basil",
        "person": "bc491ce0-17d5-4def-81ed-57a04eb74b72",
        "date": "2026-01-28T20:00:36.665Z",
        "duration": 6789,
        "billable": true,
        "billed": false,
        "status": "pending",
        "approvedBy": null,
        "approvedOn": null,
        "rejectReason": null
    },
    {
        "id": "73d8a4eb-e0e9-448e-a2bb-614200f2b5d4",
        "task": "6a91c4c9-e35c-49bb-9f70-3d56739c8d5e",
        "description": "Worked on Weeding",
        "person": "c8ae456d-4766-4d5c-a054-93bd08792bc9",
        "date": "2026-01-31T20:00:36.665Z",
        "duration": 4542,
        "billable": true,
        "billed": false,
        "status": "pending",
        "approvedBy": null,
        "approvedOn": null,
        "rejectReason": null
    },
    {
        "id": "75cfc850-929e-4fcc-85bb-a23447566551",
        "task": "9d321eeb-0213-4497-bea1-e72406d15c66",
        "description": "Worked on Prune Roses",
        "person": "fa892418-2cfb-4a37-8d7a-3838c2d03809",
        "date": "2026-01-28T20:00:36.665Z",
        "duration": 5158,
        "billable": true,
        "billed": false,
        "status": "pending",
        "approvedBy": null,
        "approvedOn": null,
        "rejectReason": null
    },
    {
        "id": "c4232ba4-f669-49b6-98df-9765894fd4a4",
        "task": "e5a076da-25c5-4845-85fa-3301cbfd0144",
        "description": "Worked on Repair Fence",
        "person": "06d4f920-4891-43d1-8710-1ff43a1188af",
        "date": "2026-02-01T20:00:36.665Z",
        "duration": 1925,
        "billable": true,
        "billed": false,
        "status": "pending",
        "approvedBy": null,
        "approvedOn": null,
        "rejectReason": null
    },
    {
        "id": "77ab0288-1747-42a7-bb71-324d77667d03",
        "task": "2ddb9c19-4827-4700-b0f3-e41ec8f07edb",
        "description": "Worked on Buy Seeds (2)",
        "person": "ff231a94-c081-44ba-affc-7af6035e5448",
        "date": "2026-01-29T20:00:36.665Z",
        "duration": 3950,
        "billable": true,
        "billed": false,
        "status": "pending",
        "approvedBy": null,
        "approvedOn": null,
        "rejectReason": null
    },
    {
        "id": "8e41585a-d8d9-457e-b4f8-e0b433abd8f2",
        "task": "ec48027b-4d42-4ab2-b4dd-99b8f521d311",
        "description": "Worked on Plant Tomatoes (2)",
        "person": "f0e168b1-5070-4b10-8499-451692315626",
        "date": "2026-02-01T20:00:36.665Z",
        "duration": 3599,
        "billable": true,
        "billed": false,
        "status": "pending",
        "approvedBy": null,
        "approvedOn": null,
        "rejectReason": null
    },
    {
        "id": "c80f5021-ff6b-4fc0-8087-192ffe194a56",
        "task": "9c2fa842-21b9-4c9a-9a7b-c4b03cf9ea6f",
        "description": "Worked on Plant Basil (2)",
        "person": "597b33f9-5acd-45ea-b953-0d3727b98931",
        "date": "2026-01-31T20:00:36.665Z",
        "duration": 2203,
        "billable": true,
        "billed": false,
        "status": "pending",
        "approvedBy": null,
        "approvedOn": null,
        "rejectReason": null
    },
    {
        "id": "94be61c2-0aef-418f-ac7f-d950daaa0f22",
        "task": "86035600-0340-4106-8fdb-a17781cf7fa2",
        "description": "Worked on Clean Tools (2)",
        "person": "212a40e4-a026-479c-85bf-64eb9e575899",
        "date": "2026-01-29T20:00:36.665Z",
        "duration": 4114,
        "billable": true,
        "billed": false,
        "status": "pending",
        "approvedBy": null,
        "approvedOn": null,
        "rejectReason": null
    },
    {
        "id": "6be04e94-7666-48d2-b23b-b691fd4d6652",
        "task": "61af32ac-54fc-4810-9984-8ef891b52b1f",
        "description": "Worked on Order Fertilizer (2)",
        "person": "8813b727-76cf-499a-a4fa-85a4d59dc0bf",
        "date": "2026-02-01T20:00:36.665Z",
        "duration": 3884,
        "billable": true,
        "billed": false,
        "status": "pending",
        "approvedBy": null,
        "approvedOn": null,
        "rejectReason": null
    },
    {
        "id": "623b1935-d1a0-4a52-a1cf-b8e3885761c2",
        "task": "e8763f8a-c26c-4f72-8ac8-9369aac9277b",
        "description": "Worked on Water Plants (3)",
        "person": "39bbbe3f-d575-4770-864c-e25da8b2df4a",
        "date": "2026-01-31T20:00:36.665Z",
        "duration": 2315,
        "billable": true,
        "billed": false,
        "status": "pending",
        "approvedBy": null,
        "approvedOn": null,
        "rejectReason": null
    },
    {
        "id": "fa415ece-2b87-4c60-ac34-0cabcc143225",
        "task": "7f382d60-7041-4564-8737-d26ea2b2d9e1",
        "description": "Worked on Prune Roses (3)",
        "person": "8e88c8a2-cba7-4ddb-9659-d352aa0989a3",
        "date": "2026-01-28T20:00:36.665Z",
        "duration": 5047,
        "billable": true,
        "billed": false,
        "status": "pending",
        "approvedBy": null,
        "approvedOn": null,
        "rejectReason": null
    },
    {
        "id": "494ca57f-f88c-43a9-9d93-e3481feb09d6",
        "task": "2d5749a1-06e4-4bc8-b6c0-7ff8831c18ca",
        "description": "Worked on Buy Seeds (4)",
        "person": "ca8b6fb6-c7e9-4509-94fd-1092845250f1",
        "date": "2026-01-28T20:00:36.665Z",
        "duration": 3243,
        "billable": true,
        "billed": false,
        "status": "pending",
        "approvedBy": null,
        "approvedOn": null,
        "rejectReason": null
    },
    {
        "id": "4ecfe0a5-bf2b-430b-b556-8349f61c40a4",
        "task": "b40c8d68-bf28-462b-b806-960f26979a2c",
        "description": "Worked on Plant Tomatoes (4)",
        "person": "b54f0dca-1584-4d65-b2e7-9be8cce95405",
        "date": "2026-01-28T20:00:36.665Z",
        "duration": 2002,
        "billable": true,
        "billed": false,
        "status": "pending",
        "approvedBy": null,
        "approvedOn": null,
        "rejectReason": null
    },
    {
        "id": "10f75db2-3ad6-4e40-af49-3a3aa41fd12b",
        "task": "c87be68a-e6fe-4436-891b-f21e3fb68817",
        "description": "Worked on Plant Basil (4)",
        "person": "181ba948-dd30-4924-8df9-38eb7025537f",
        "date": "2026-01-28T20:00:36.665Z",
        "duration": 4306,
        "billable": true,
        "billed": false,
        "status": "pending",
        "approvedBy": null,
        "approvedOn": null,
        "rejectReason": null
    },
    {
        "id": "7285c304-fc06-422d-a957-b1875a9d88c9",
        "task": "ae49daea-dec1-443f-b3de-97619d810d32",
        "description": "Worked on Mulching (4)",
        "person": "c70cb0bd-6ea7-45f0-902d-e8a9f61fcec2",
        "date": "2026-01-31T20:00:36.665Z",
        "duration": 4629,
        "billable": true,
        "billed": false,
        "status": "pending",
        "approvedBy": null,
        "approvedOn": null,
        "rejectReason": null
    },
    {
        "id": "3dc67637-9049-4310-a64d-e67ba4b3e70a",
        "task": "05e6ecc9-5790-47bd-82a2-1a851fa942d8",
        "description": "Worked on Harvest Carrots (4)",
        "person": "e17f718c-e1f8-4d8d-b644-6565eb3854f8",
        "date": "2026-02-01T20:00:36.665Z",
        "duration": 2032,
        "billable": true,
        "billed": false,
        "status": "pending",
        "approvedBy": null,
        "approvedOn": null,
        "rejectReason": null
    },
    {
        "id": "8446be36-2e23-445c-b2be-ca03ce4e0b06",
        "task": "ab98d52c-7a06-46a4-81f1-49aa5c300c0e",
        "description": "Worked on Repair Fence (4)",
        "person": "d12545dc-61e0-41b5-bb7a-ea004f37a09c",
        "date": "2026-01-31T20:00:36.665Z",
        "duration": 4557,
        "billable": true,
        "billed": false,
        "status": "pending",
        "approvedBy": null,
        "approvedOn": null,
        "rejectReason": null
    },
    {
        "id": "c0a41901-7b9e-4a60-a849-ff8b6d98c92a",
        "task": "2b238596-0e0b-48d5-8ee5-20e0a83eeece",
        "description": "Worked on Buy Seeds (5)",
        "person": "6ba434fb-d2b1-4ce1-a677-c15939ada2b3",
        "date": "2026-02-02T20:00:36.665Z",
        "duration": 3763,
        "billable": true,
        "billed": false,
        "status": "pending",
        "approvedBy": null,
        "approvedOn": null,
        "rejectReason": null
    }
]